setup.py
seznam_captcha.py
seznam_captcha.egg-info/PKG-INFO
seznam_captcha.egg-info/SOURCES.txt
seznam_captcha.egg-info/dependency_links.txt
seznam_captcha.egg-info/not-zip-safe
seznam_captcha.egg-info/requires.txt
seznam_captcha.egg-info/top_level.txt