Metadata-Version: 1.1
Name: seznam-captcha
Version: 1.2.1
Summary: Wraper for Seznam Captcha
Home-page: https://github.com/sikaondrej/seznam-captcha/
Author: Ondrej Sika
Author-email: UNKNOWN
License: MIT Licence
Download-URL: https://github.com/sikaondrej/seznam-captcha/
Platform: UNKNOWN
